tsp_brouter/__init__.py
tsp_brouter/brouter_call.py
tsp_brouter/ogr_helper.py
tsp_brouter/ortools_tsp.py
tsp_brouter/tsp_brouter.py
tsp_brouter-0.1.1.data/scripts/tsp_brouter_cli.py
tsp_brouter-0.1.1.dist-info/LICENSE
tsp_brouter-0.1.1.dist-info/METADATA
tsp_brouter-0.1.1.dist-info/WHEEL
tsp_brouter-0.1.1.dist-info/top_level.txt
tsp_brouter-0.1.1.dist-info/RECORD
