Metadata-Version: 2.1
Name: tsp-brouter
Version: 0.1.1
Summary: A Python CLI script to run travelling salesman problem (tsp) algorithms using brouter routing times.
Home-page: https://github.com/bryandenniskeith/tsp_brouter
Author: Bryan Keith
Author-email: bryandenniskeith@gmail.com
License: UNKNOWN
Project-URL: Bug Tracker, https://github.com/bryandenniskeith/tsp_brouter/issues
Platform: UNKNOWN
Classifier: Programming Language :: Python :: 3
Classifier: License :: OSI Approved :: MIT License
Classifier: Operating System :: OS Independent
Requires-Python: >=3.6
License-File: LICENSE
Requires-Dist: urllib3
Requires-Dist: ortools
